README.md
setup.py
face_ai/__init__.py
face_ai.egg-info/PKG-INFO
face_ai.egg-info/SOURCES.txt
face_ai.egg-info/dependency_links.txt
face_ai.egg-info/requires.txt
face_ai.egg-info/top_level.txt