Metadata-Version: 2.1
Name: face-ai
Version: 0.0.1
Summary: Package for Face AI, including Face Detection & Face Recognition
Home-page: https://www.ai.game.tw
Author: BIG CHENG
Author-email: bigcheng.asus@gmail.com
License: UNKNOWN
Platform: UNKNOWN
Classifier: Programming Language :: Python :: 3
Classifier: License :: OSI Approved :: MIT License
Classifier: Operating System :: OS Independent
